mailmate
tests
