Metadata-Version: 1.1
Name: django-mailmate
Version: 1.3.0
Summary: Django email tools.
Home-page: http://github.com/hzdg/django-mailmate
Author: Chris McKenzie
Author-email: chrismc@hzdg.com
License: MIT
Platform: UNKNOWN
Classifier: Environment :: Web Environment
Classifier: Framework :: Django
Classifier: Intended Audience :: Developers
Classifier: Operating System :: OS Independent
Classifier: Programming Language :: Python
Classifier: Topic :: Internet :: WWW/HTTP
